discord_to_sqlite/__init__.py
discord_to_sqlite/cli.py
discord_to_sqlite/utils.py
discord_to_sqlite-0.2.dist-info/LICENSE
discord_to_sqlite-0.2.dist-info/METADATA
discord_to_sqlite-0.2.dist-info/WHEEL
discord_to_sqlite-0.2.dist-info/entry_points.txt
discord_to_sqlite-0.2.dist-info/top_level.txt
discord_to_sqlite-0.2.dist-info/RECORD
