Metadata-Version: 2.1
Name: discord-to-sqlite
Version: 0.2
Summary: Save data from Discord to a SQLite database
Home-page: https://github.com/troennes/discord-to-sqlite
Author: Kim Trønnes
License: Apache License, Version 2.0
Platform: UNKNOWN
Classifier: Programming Language :: Python :: 3
Classifier: Operating System :: OS Independent
Requires-Python: >3.6
Requires-Dist: sqlite-utils (>=2.8)
Provides-Extra: test
Requires-Dist: pytest ; extra == 'test'
